infinario.py
infinario-2.0.1.dist-info/metadata.json
infinario-2.0.1.dist-info/METADATA
infinario-2.0.1.dist-info/WHEEL
infinario-2.0.1.dist-info/top_level.txt
infinario-2.0.1.dist-info/RECORD
infinario-2.0.1.dist-info/DESCRIPTION.rst
